{"type": "Feature", "id": 12522706, "geometry": {"type": "Point", "coordinates": [66.753197, 39.070099]}, "properties": {"woe:id": 12522706, "woe:parent_id": 2271484, "woe:name": "Shakhrisyabz Airport", "woe:placetype": 14, "woe:placetype_name": "Airport", "woe:lang": "ENG", "iso:country": "UZ", "meta:provider": ["geoplanet:7.3.1", "geoplanet:7.3.2", "geoplanet:7.4.0", "geoplanet:7.4.1", "geoplanet:7.5.1", "geoplanet:7.5.2", "geoplanet:7.6.0", "geoplanet:7.8.1", "geoplanet:7.9.0", "geoplanet:7.10.0", "geoplanet:8.0.0", "woeplanet:8.0.0"], "meta:indexed": "2020-08-20T20:51:59.976164", "meta:updated": "2020-10-14T11:06:45.908310", "woe:hierarchy": {"continent": 24865671, "country": 23424980, "town": 0, "planet": 1, "county": 0, "suburb": 0, "state": 2347664, "region": 0, "localadmin": 0}, "woe:timezone_id": 56043643, "woe:hash": "tqzqr02py4r6", "woe:centroid": [66.753197, 39.070099], "geom:latitude": 39.070099, "geom:longitude": 66.753197, "geom:hash": "tqzqr02py4r6", "woe:latitude": 39.070099, "geom:centroid": [66.753197, 39.070099], "woe:longitude": 66.753197, "woe:repo": "woeplanet-airport-uz", "geom:area": 0.0, "woe:scale": 19}}