{"type": "Feature", "id": 12522591, "geometry": {"type": "Point", "coordinates": [69.042603, 40.9491]}, "properties": {"woe:id": 12522591, "woe:parent_id": 2269265, "woe:name": "Chartak Airport", "woe:placetype": 14, "woe:placetype_name": "Airport", "woe:lang": "ENG", "iso:country": "UZ", "meta:provider": ["geoplanet:7.3.1", "geoplanet:7.3.2", "geoplanet:7.4.0", "geoplanet:7.4.1", "geoplanet:7.5.1", "geoplanet:7.5.2", "geoplanet:7.6.0", "geoplanet:7.8.1", "geoplanet:7.9.0", "geoplanet:7.10.0", "geoplanet:8.0.0", "woeplanet:8.0.0"], "meta:indexed": "2020-08-20T20:51:59.889203", "meta:updated": "2020-10-14T11:06:45.873252", "woe:hierarchy": {"continent": 24865671, "country": 23424980, "town": 0, "planet": 1, "county": 0, "suburb": 0, "state": 2347670, "region": 0, "localadmin": 0}, "woe:timezone_id": 56043642, "woe:hash": "tx30gne3c380", "woe:centroid": [69.042603, 40.9491], "geom:latitude": 40.9491, "geom:longitude": 69.042603, "geom:hash": "tx30gne3c380", "woe:latitude": 40.9491, "geom:centroid": [69.042603, 40.9491], "woe:longitude": 69.042603, "woe:repo": "woeplanet-airport-uz", "geom:area": 0.0, "woe:scale": 19}}