{"type": "Feature", "id": 12522582, "properties": {"woe:id": 12522582, "woe:parent_id": 2269239, "woe:name": "Balykchi Southwest Airport", "woe:placetype": 14, "woe:placetype_name": "Airport", "woe:lang": "ENG", "iso:country": "UZ", "meta:provider": ["geoplanet:7.3.1", "geoplanet:7.3.2", "geoplanet:7.4.0", "geoplanet:7.4.1", "geoplanet:7.5.1", "geoplanet:7.5.2", "geoplanet:7.6.0", "geoplanet:7.8.1", "geoplanet:7.9.0", "geoplanet:7.10.0", "geoplanet:8.0.0", "woeplanet:8.0.0"], "meta:indexed": "2020-08-20T20:51:59.881809", "meta:updated": "2020-08-22T01:57:41.959427", "woe:hierarchy": {"continent": 24865671, "country": 23424980, "town": 0, "planet": 1, "county": 0, "suburb": 0, "state": 2347659, "region": 0, "localadmin": 0}, "woe:timezone_id": 56043642, "woe:hash": "tx702drtw2kg", "woe:centroid": [71.751297, 40.838501], "geom:latitude": 40.838501, "geom:longitude": 71.751297, "geom:hash": "tx702drtw2kg", "woe:latitude": 40.838501, "geom:centroid": [71.751297, 40.838501], "woe:longitude": 71.751297, "woe:repo": "woeplanet-airport-uz"}, "geometry": {"coordinates": [71.751297, 40.838501], "type": "Point"}}