{"type": "Feature", "id": 12522608, "properties": {"woe:id": 12522608, "woe:parent_id": 2270002, "woe:name": "Dzhamby Airport", "woe:placetype": 14, "woe:placetype_name": "Airport", "woe:lang": "ENG", "iso:country": "UZ", "meta:provider": ["geoplanet:7.3.1", "geoplanet:7.3.2", "geoplanet:7.4.0", "geoplanet:7.4.1", "geoplanet:7.5.1", "geoplanet:7.5.2", "geoplanet:7.6.0", "geoplanet:7.8.1", "geoplanet:7.9.0", "geoplanet:7.10.0", "geoplanet:8.0.0", "woeplanet:8.0.0"], "meta:indexed": "2020-08-20T20:51:59.903135", "meta:updated": "2020-08-22T01:57:41.971728", "woe:hierarchy": {"continent": 24865671, "country": 23424980, "town": 0, "planet": 1, "county": 0, "suburb": 0, "state": 20070173, "region": 0, "localadmin": 0}, "woe:timezone_id": 56043643, "woe:hash": "trpc8qhr2uu0", "woe:centroid": [67.165298, 39.672901], "geom:latitude": 39.672901, "geom:longitude": 67.165298, "geom:hash": "trpc8qhr2uu0", "woe:latitude": 39.672901, "geom:centroid": [67.165298, 39.672901], "woe:longitude": 67.165298, "woe:repo": "woeplanet-airport-uz"}, "geometry": {"coordinates": [67.165298, 39.672901], "type": "Point"}}