{"type": "Feature", "id": 12522745, "geometry": {"type": "Point", "coordinates": [70.927299, 40.3806]}, "properties": {"woe:id": 12522745, "woe:parent_id": 2272665, "woe:name": "Yaydan Northeast Airport", "woe:placetype": 14, "woe:placetype_name": "Airport", "woe:lang": "ENG", "iso:country": "UZ", "meta:provider": ["geoplanet:7.3.1", "geoplanet:7.3.2", "geoplanet:7.4.0", "geoplanet:7.4.1", "geoplanet:7.5.1", "geoplanet:7.5.2", "geoplanet:7.6.0", "geoplanet:7.8.1", "geoplanet:7.9.0", "geoplanet:7.10.0", "geoplanet:8.0.0", "woeplanet:8.0.0"], "meta:indexed": "2020-08-20T20:52:00.008958", "meta:updated": "2020-10-14T11:06:45.890271", "woe:hierarchy": {"continent": 24865671, "country": 23424980, "town": 0, "planet": 1, "county": 0, "suburb": 0, "state": 2347662, "region": 0, "localadmin": 0}, "woe:timezone_id": 56043642, "woe:hash": "tx4mtzpdjc7m", "woe:centroid": [70.927299, 40.3806], "geom:latitude": 40.3806, "geom:longitude": 70.927299, "geom:hash": "tx4mtzpdjc7m", "woe:latitude": 40.3806, "geom:centroid": [70.927299, 40.3806], "woe:longitude": 70.927299, "woe:repo": "woeplanet-airport-uz", "geom:area": 0.0, "woe:scale": 19}}