{"type": "Feature", "id": 12522613, "geometry": {"type": "Point", "coordinates": [65.788101, 38.745701]}, "properties": {"woe:id": 12522613, "woe:parent_id": 2272581, "woe:name": "Fayzabad Airport", "woe:placetype": 14, "woe:placetype_name": "Airport", "woe:lang": "ENG", "iso:country": "UZ", "meta:provider": ["geoplanet:7.3.1", "geoplanet:7.3.2", "geoplanet:7.4.0", "geoplanet:7.4.1", "geoplanet:7.5.1", "geoplanet:7.5.2", "geoplanet:7.6.0", "geoplanet:7.8.1", "geoplanet:7.9.0", "geoplanet:7.10.0", "geoplanet:8.0.0", "woeplanet:8.0.0"], "meta:indexed": "2020-08-20T20:51:59.907150", "meta:updated": "2020-10-14T11:06:45.951927", "woe:hierarchy": {"continent": 24865671, "country": 23424980, "town": 0, "planet": 1, "county": 0, "suburb": 0, "state": 2347664, "region": 0, "localadmin": 0}, "woe:timezone_id": 56043643, "woe:hash": "tqyu3j3qjf5t", "woe:centroid": [65.788101, 38.745701], "geom:latitude": 38.745701, "geom:longitude": 65.788101, "geom:hash": "tqyu3j3qjf5t", "woe:latitude": 38.745701, "geom:centroid": [65.788101, 38.745701], "woe:longitude": 65.788101, "woe:repo": "woeplanet-airport-uz", "geom:area": 0.0, "woe:scale": 19}}