{"type": "Feature", "id": 12522635, "geometry": {"type": "Point", "coordinates": [71.185204, 40.810902]}, "properties": {"woe:id": 12522635, "woe:parent_id": 2270272, "woe:name": "Kara Kalpak Airport", "woe:placetype": 14, "woe:placetype_name": "Airport", "woe:lang": "ENG", "iso:country": "UZ", "meta:provider": ["geoplanet:7.3.1", "geoplanet:7.3.2", "geoplanet:7.4.0", "geoplanet:7.4.1", "geoplanet:7.5.1", "geoplanet:7.5.2", "geoplanet:7.6.0", "geoplanet:7.8.1", "geoplanet:7.9.0", "geoplanet:7.10.0", "geoplanet:8.0.0", "woeplanet:8.0.0"], "meta:indexed": "2020-08-20T20:51:59.922499", "meta:updated": "2020-10-14T11:06:45.927426", "woe:hierarchy": {"continent": 24865671, "country": 23424980, "town": 0, "planet": 1, "county": 0, "suburb": 0, "state": 2347666, "region": 0, "localadmin": 0}, "woe:timezone_id": 56043642, "woe:hash": "tx685v7kxrx3", "woe:centroid": [71.185204, 40.810902], "geom:latitude": 40.810902, "geom:longitude": 71.185204, "geom:hash": "tx685v7kxrx3", "woe:latitude": 40.810902, "geom:centroid": [71.185204, 40.810902], "woe:longitude": 71.185204, "woe:repo": "woeplanet-airport-uz", "geom:area": 0.0, "woe:scale": 19}}