{"type": "Feature", "id": 12522649, "properties": {"woe:id": 12522649, "woe:parent_id": 2272648, "woe:name": "Kayki Airport", "woe:placetype": 14, "woe:placetype_name": "Airport", "woe:lang": "ENG", "iso:country": "UZ", "meta:provider": ["geoplanet:7.3.1", "geoplanet:7.3.2", "geoplanet:7.4.0", "geoplanet:7.4.1", "geoplanet:7.5.1", "geoplanet:7.5.2", "geoplanet:7.6.0", "geoplanet:7.8.1", "geoplanet:7.9.0", "geoplanet:7.10.0", "geoplanet:8.0.0", "woeplanet:8.0.0"], "meta:indexed": "2020-08-20T20:51:59.930550", "meta:updated": "2020-08-22T01:57:41.983610", "woe:hierarchy": {"continent": 24865671, "country": 23424980, "town": 0, "planet": 1, "county": 0, "suburb": 0, "state": 2347666, "region": 0, "localadmin": 0}, "woe:timezone_id": 56043642, "woe:hash": "tx71xnwg7dxr", "woe:centroid": [72.035797, 41.0812], "geom:latitude": 41.0812, "geom:longitude": 72.035797, "geom:hash": "tx71xnwg7dxr", "woe:latitude": 41.0812, "geom:centroid": [72.035797, 41.0812], "woe:longitude": 72.035797, "woe:repo": "woeplanet-airport-uz"}, "geometry": {"coordinates": [72.035797, 41.0812], "type": "Point"}}