{"type": "Feature", "id": 12522574, "geometry": {"type": "Point", "coordinates": [66.651398, 39.921101]}, "properties": {"woe:id": 12522574, "woe:parent_id": 2272402, "woe:name": "Akdarya Airport", "woe:placetype": 14, "woe:placetype_name": "Airport", "woe:lang": "ENG", "iso:country": "UZ", "meta:provider": ["geoplanet:7.3.1", "geoplanet:7.3.2", "geoplanet:7.4.0", "geoplanet:7.4.1", "geoplanet:7.5.1", "geoplanet:7.5.2", "geoplanet:7.6.0", "geoplanet:7.8.1", "geoplanet:7.9.0", "geoplanet:7.10.0", "geoplanet:8.0.0", "woeplanet:8.0.0"], "meta:indexed": "2020-08-20T20:51:59.875115", "meta:updated": "2020-10-14T11:06:45.877926", "woe:hierarchy": {"continent": 24865671, "country": 23424980, "town": 0, "planet": 1, "county": 0, "suburb": 0, "state": 20070173, "region": 0, "localadmin": 0}, "woe:timezone_id": 56043643, "woe:hash": "trp7heqj60s7", "woe:centroid": [66.651398, 39.921101], "geom:latitude": 39.921101, "geom:longitude": 66.651398, "geom:hash": "trp7heqj60s7", "woe:latitude": 39.921101, "geom:centroid": [66.651398, 39.921101], "woe:longitude": 66.651398, "woe:repo": "woeplanet-airport-uz", "geom:area": 0.0, "woe:scale": 19}}